{
  "basics": {
    "name": "Tyler Chong",
    "label": "Student",
    "picture": "https://viltaria.github.io/images/profile.jpg",
    "email": "tcchong@hawaii.edu",
    "phone": "808-388-0313",
    "website": "https://viltaria.github.io",
    "summary": "I am studying for a B.S. in Computer Science in the Department of Information and Computer Sciences at the University of Hawaii. I expect to graduate in Fall, 2020.",
    "location": {
      "address": "University of Hawaii at Manoa",
      "postalCode": "96822",
      "city": "Honolulu",
      "countryCode": "USA",
      "region": "Hawaii"
    },
    "profiles": [
      {
        "network": "Github",
        "username": "Viltaria",
        "url": "http://github.com/Viltaria"
      },
      {
        "network": "Linkedin",
        "username": "chongtyler",
        "url": "https://www.linkedin.com/in/chongtyler"
      }
    ]
  },
  "interests": [
    {
      "name": "Internet of Things",
      "keywords": [
        "Arduino",
        "Rasberry PI"
      ]
    },
    {
      "name": "Data Mining",
      "keywords": [
        "Selenium"
      ]
    },
    {
      "name": "Cyber Security",
      "keywords": [
        "Grey Hats"
      ]
    },
    {
      "name": "",
      "keywords": []
    }
  ],
  "skills": [
    {
      "name": "Languages and Frameworks",
      "level": "",
      "keywords": [
        "Java",
        "Javascript",
        "Python",
        "C",
        "C++",
        "SQL"
      ]
    },
    {
      "name": "Toolsets/OS",
      "level": "",
      "keywords": [
        "MacOS",
        "Ubuntu",
        "Git/GitHub",
        "g++",
        "TI LaunchPad"
      ]
    }
  ],
  "education": [
    {
      "institution": "University of Hawaii, Honolulu, HI",
      "area": "Computer Science (expected Spring, 2020)",
      "studyType": "B.S.",
      "startDate": "2016-09-01",
      "endDate": "Present",
      "gpa": "3.5",
      "courses": []
    }
  ],
  "work": [
    {
      "company": "",
      "position": "",
      "website": "",
      "startDate": "",
      "endDate": "",
      "summary": "",
      "highlights": [
        ""
      ]
    }
  ],
  "volunteer": [
    {
      "organization": "",
      "website": "",
      "position": "Professional organization involvement",
      "startDate": "",
      "endDate": "",
      "summary": "",
      "highlights": [
        "President, UHM Grey Hats, 2016-Present",
        "Member, ACM Manoa, 2016-Present"
      ]
    }
  ],
  "awards": [
    {
      "title": "Summer Launchpad Certificate of Completetion",
      "date": "June 2017",
      "awarder": "Pacific Asian Center for Entrepreneurship",
      "summary": "Participated in a Summer Launchpad that trains entrepreneurs."
    },
    {
      "title": "CompTIA A+ 901 Exam Certification",
      "date": "August 2017 - September 2020",
      "awarder": "CompTIA",
      "summary": ""
    },
    {
      "title": "Pynight: Python Programming Competition Winner",
      "date": "June 2017",
      "awarder": "Booz Allen",
      "summary": "Defeated the competition at a Python Programming Competition hosted by Booz Allen. Part of Team \"Azure\"."
    },
    {
      "title": "NASA Space Apps Challenge Hackathon People's Choice Winner",
      "date": "May 2017",
      "awarder": "NASA",
      "summary": "Won \"Best Creative\" on Fly!, a 3D flight simulator for kid passengers to explore what's beneath their flight using custom 3D models and controls. Users can fly around the globe and see what the weather is like through animations. They can also check to see what's nearby."
    }
  ],
  "references": [
    {
      "name": "Available upon request",
      "reference": ""
    }
  ]
}